{
  "version": "0.2",
  "language": "en",
  "words": [
    "biomejs",
    "codex",
    "deadcode",
    "evals",
    "ffgrep",
    "fffind",
    "frontmatter",
    "gocyclo",
    "golangci",
    "HSTS",
    "impls",
    "infrasys",
    "khala",
    "markdownlint",
    "overfit",
    "prek",
    "PRNG",
    "pydeps",
    "sandboxing",
    "subagent",
    "subagents",
    "subcomponents",
    "torc",
    "typecheck",
    "udeps",
    "untangler",
    "Unvalidated",
    "vaultwarden",
    "worktree",
    "worktrees",
    "yamllint"
  ],
  "ignorePaths": [
    "node_modules",
    ".git",
    ".pi",
    "*.csv",
    "*.json",
    "*.lock",
    "package-lock.json"
  ],
  "dictionaries": ["typescript", "python", "rust", "bash", "npm"],
  "enableFiletypes": ["markdown", "yaml", "toml", "typescript"]
}
